aioworkers/__init__.py
aioworkers/__main__.py
aioworkers/cli.py
aioworkers/http.py
aioworkers/humanize.py
aioworkers/py.typed
aioworkers/utils.py
aioworkers/core/__init__.py
aioworkers/core/base.py
aioworkers/core/command.py
aioworkers/core/config.py
aioworkers/core/context.py
aioworkers/core/formatter.py
aioworkers/core/interact.py
aioworkers/core/plugin.py
aioworkers/net/__init__.py
aioworkers/net/server.py
aioworkers/net/uri.py
aioworkers/net/sender/__init__.py
aioworkers/net/sender/proxy.py
aioworkers/net/sender/smtp.py
aioworkers/net/web/__init__.py
aioworkers/net/web/app.py
aioworkers/net/web/asgi.py
aioworkers/net/web/client.py
aioworkers/net/web/exceptions.py
aioworkers/net/web/headers.py
aioworkers/net/web/protocol.py
aioworkers/net/web/request.py
aioworkers/net/web/server.py
aioworkers/queue/__init__.py
aioworkers/queue/base.py
aioworkers/queue/csv.py
aioworkers/queue/proxy.py
aioworkers/queue/timeout.py
aioworkers/storage/__init__.py
aioworkers/storage/base.py
aioworkers/storage/filesystem.py
aioworkers/storage/http.py
aioworkers/storage/meta.py
aioworkers/worker/__init__.py
aioworkers/worker/base.py
aioworkers/worker/subprocess.py
aioworkers/worker/supervisor.py
aioworkers/worker/updater.py
aioworkers-0.28.0.dist-info/METADATA
aioworkers-0.28.0.dist-info/WHEEL
aioworkers-0.28.0.dist-info/entry_points.txt
aioworkers-0.28.0.dist-info/licenses/LICENSE
aioworkers-0.28.0.dist-info/RECORD
