Metadata-Version: 2.4
Name: aioworkers
Version: 0.28.0
Summary: Easy configurable workers based on asyncio
Project-URL: Homepage, https://github.com/aioworkers/aioworkers
Project-URL: Documentation, https://aioworkers.readthedocs.io
Project-URL: Issues, https://github.com/aioworkers/aioworkers/issues
Project-URL: Source, https://github.com/aioworkers/aioworkers
Author-email: Alexander Malev <malev@somedev.ru>
License-Expression: Apache-2.0
License-File: LICENSE
Keywords: aioworkers
Classifier: Development Status :: 5 - Production/Stable
Classifier: Framework :: AsyncIO
Classifier: Intended Audience :: Developers
Classifier: License :: OSI Approved :: Apache Software License
Classifier: Programming Language :: Python :: 3
Classifier: Programming Language :: Python :: 3 :: Only
Classifier: Programming Language :: Python :: 3.8
Classifier: Programming Language :: Python :: 3.9
Classifier: Programming Language :: Python :: 3.10
Classifier: Programming Language :: Python :: 3.11
Classifier: Programming Language :: Python :: 3.12
Classifier: Programming Language :: Python :: 3.13
Classifier: Programming Language :: Python :: Implementation :: CPython
Classifier: Programming Language :: Python :: Implementation :: PyPy
Requires-Python: >=3.8
Provides-Extra: aiohttp
Requires-Dist: aioworkers-aiohttp; extra == 'aiohttp'
Requires-Dist: uvloop; extra == 'aiohttp'
Provides-Extra: cron
Requires-Dist: crontab; extra == 'cron'
Provides-Extra: dev-interactive
Requires-Dist: ipykernel==6.29.5; extra == 'dev-interactive'
Requires-Dist: ipython==8.30.0; extra == 'dev-interactive'
Provides-Extra: dev-lint
Requires-Dist: mypy==1.14.0; extra == 'dev-lint'
Requires-Dist: ruff==0.8.4; extra == 'dev-lint'
Requires-Dist: types-pyyaml; extra == 'dev-lint'
Requires-Dist: types-setuptools; extra == 'dev-lint'
Provides-Extra: dev-test
Requires-Dist: bson==0.5.10; extra == 'dev-test'
Requires-Dist: coverage[toml]==7.6.1; extra == 'dev-test'
Requires-Dist: httptools==0.6.4; extra == 'dev-test'
Requires-Dist: msgpack==1.1.0; extra == 'dev-test'
Requires-Dist: pytest-aioworkers[asyncio]==0.4.0; extra == 'dev-test'
Requires-Dist: pytest-mock==3.14.0; extra == 'dev-test'
Requires-Dist: pytest-timeout==2.3.1; extra == 'dev-test'
Requires-Dist: pytest==8.3.4; extra == 'dev-test'
Requires-Dist: pyyaml==6.0.2; extra == 'dev-test'
Provides-Extra: interactive
Requires-Dist: ipykernel; extra == 'interactive'
Provides-Extra: prometheus
Requires-Dist: aioworkers-prometheus; extra == 'prometheus'
Provides-Extra: sentry
Requires-Dist: aioworkers-sentry; extra == 'sentry'
Provides-Extra: toml
Requires-Dist: tomli; (python_version < '3.11') and extra == 'toml'
Provides-Extra: web
Requires-Dist: httptools; extra == 'web'
Requires-Dist: pyyaml; extra == 'web'
Requires-Dist: uvloop; extra == 'web'
